Metadata-Version: 2.1
Name: tpify
Version: 0.0.1a3
Summary: Return, don't raise.
Author-email: Kyle Shaver <kyle@tpify.dev>
Project-URL: Homepage, https://github.com/KyleJShaver/tpify
Project-URL: Issues, https://github.com/KyleJShaver/tpify/issues
Classifier: Programming Language :: Python :: 3
Classifier: License :: OSI Approved :: MIT License
Classifier: Operating System :: OS Independent
Requires-Python: >=3.8
License-File: LICENSE
Provides-Extra: dev
Requires-Dist: pytest; extra == "dev"
Requires-Dist: pytest-cov; extra == "dev"
